<?xml version="1.0" encoding="utf-8" standalone="yes"?>
<imgdir name="9062761.img">
    <imgdir name="info">
        <int name="hideName" value="1" />
    </imgdir>
    <imgdir name="stand">
        <canvas name="0" width="95" height="102">
            <vector name="origin" x="62" y="102" />
            <int name="z" value="0" />
        </canvas>
        <canvas name="1" width="96" height="102">
            <vector name="origin" x="63" y="102" />
            <int name="z" value="0" />
        </canvas>
        <canvas name="2" width="96" height="102">
            <vector name="origin" x="63" y="102" />
            <int name="z" value="0" />
        </canvas>
        <canvas name="3" width="96" height="102">
            <vector name="origin" x="63" y="102" />
            <int name="z" value="0" />
        </canvas>
        <canvas name="4" width="96" height="102">
            <vector name="origin" x="63" y="102" />
            <int name="z" value="0" />
        </canvas>
        <canvas name="5" width="98" height="102">
            <vector name="origin" x="65" y="102" />
            <int name="z" value="0" />
        </canvas>
        <canvas name="6" width="93" height="102">
            <vector name="origin" x="60" y="102" />
            <int name="z" value="0" />
        </canvas>
        <canvas name="7" width="95" height="102">
            <vector name="origin" x="62" y="102" />
            <int name="z" value="0" />
        </canvas>
    </imgdir>
    <imgdir name="say">
        <canvas name="0" width="95" height="102">
            <vector name="origin" x="62" y="102" />
            <int name="z" value="0" />
        </canvas>
        <canvas name="1" width="96" height="102">
            <vector name="origin" x="63" y="102" />
            <int name="z" value="0" />
        </canvas>
        <canvas name="2" width="96" height="102">
            <vector name="origin" x="63" y="102" />
            <int name="z" value="0" />
        </canvas>
        <canvas name="3" width="96" height="102">
            <vector name="origin" x="63" y="102" />
            <int name="z" value="0" />
        </canvas>
        <canvas name="4" width="96" height="102">
            <vector name="origin" x="63" y="102" />
            <int name="z" value="0" />
        </canvas>
        <canvas name="5" width="98" height="102">
            <vector name="origin" x="65" y="102" />
            <int name="z" value="0" />
        </canvas>
        <canvas name="6" width="93" height="102">
            <vector name="origin" x="60" y="102" />
            <int name="z" value="0" />
        </canvas>
        <canvas name="7" width="95" height="102">
            <vector name="origin" x="62" y="102" />
            <int name="z" value="0" />
        </canvas>
    </imgdir>
    <imgdir name="eye">
        <canvas name="0" width="95" height="102">
            <vector name="origin" x="62" y="102" />
            <int name="z" value="0" />
        </canvas>
        <canvas name="1" width="96" height="102">
            <vector name="origin" x="63" y="102" />
            <int name="z" value="0" />
        </canvas>
        <canvas name="2" width="96" height="102">
            <vector name="origin" x="63" y="102" />
            <int name="z" value="0" />
        </canvas>
        <canvas name="3" width="96" height="102">
            <vector name="origin" x="63" y="102" />
            <int name="z" value="0" />
        </canvas>
        <canvas name="4" width="96" height="102">
            <vector name="origin" x="63" y="102" />
            <int name="z" value="0" />
        </canvas>
        <canvas name="5" width="98" height="102">
            <vector name="origin" x="65" y="102" />
            <int name="z" value="0" />
        </canvas>
        <canvas name="6" width="93" height="102">
            <vector name="origin" x="60" y="102" />
            <int name="z" value="0" />
        </canvas>
        <canvas name="7" width="95" height="102">
            <vector name="origin" x="62" y="102" />
            <int name="z" value="0" />
        </canvas>
    </imgdir>
</imgdir>