<?xml version="1.0" encoding="utf-8" standalone="yes"?>
<imgdir name="9062636.img">
    <imgdir name="info">
        <imgdir name="script">
            <imgdir name="0">
                <string name="script" value="npc_9062636" />
            </imgdir>
        </imgdir>
        <int name="dcLeft" value="-50" />
        <int name="dcTop" value="-96" />
        <int name="dcBottom" value="0" />
        <int name="dcRight" value="43" />
        <int name="hide" value="1" />
    </imgdir>
    <imgdir name="stand">
        <canvas name="0" width="1" height="1">
            <vector name="origin" x="0" y="0" />
            <int name="z" value="0" />
        </canvas>
    </imgdir>
    <imgdir name="eye">
        <canvas name="0" width="1" height="1">
            <vector name="origin" x="0" y="0" />
            <int name="z" value="0" />
        </canvas>
    </imgdir>
    <imgdir name="say">
        <canvas name="0" width="1" height="1">
            <vector name="origin" x="0" y="0" />
            <int name="z" value="0" />
        </canvas>
    </imgdir>
    <imgdir name="condition2">
        <imgdir name="502058">
            <imgdir name="0">
                <string name="key" value="show" />
                <string name="value" value="1" />
            </imgdir>
            <int name="hide" value="0" />
        </imgdir>
        <imgdir name="stand">
            <canvas name="0" width="109" height="118">
                <vector name="origin" x="50" y="118" />
                <int name="z" value="0" />
                <int name="delay" value="180" />
            </canvas>
            <canvas name="1" width="109" height="119">
                <vector name="origin" x="50" y="119" />
                <int name="z" value="0" />
                <int name="delay" value="180" />
            </canvas>
            <canvas name="2" width="109" height="118">
                <vector name="origin" x="50" y="118" />
                <int name="z" value="0" />
                <int name="delay" value="180" />
            </canvas>
            <canvas name="3" width="109" height="117">
                <vector name="origin" x="50" y="117" />
                <int name="z" value="0" />
                <int name="delay" value="180" />
            </canvas>
        </imgdir>
        <imgdir name="eye">
            <canvas name="0" width="109" height="118">
                <vector name="origin" x="50" y="118" />
                <int name="z" value="0" />
                <int name="delay" value="180" />
            </canvas>
            <canvas name="1" width="109" height="119">
                <vector name="origin" x="50" y="119" />
                <int name="z" value="0" />
                <int name="delay" value="180" />
            </canvas>
            <canvas name="2" width="109" height="118">
                <vector name="origin" x="50" y="118" />
                <int name="z" value="0" />
                <int name="delay" value="180" />
            </canvas>
            <canvas name="3" width="109" height="117">
                <vector name="origin" x="50" y="117" />
                <int name="z" value="0" />
                <int name="delay" value="180" />
            </canvas>
        </imgdir>
        <imgdir name="say">
            <canvas name="0" width="109" height="118">
                <vector name="origin" x="50" y="118" />
                <int name="z" value="0" />
                <int name="delay" value="180" />
            </canvas>
            <canvas name="1" width="109" height="119">
                <vector name="origin" x="50" y="119" />
                <int name="z" value="0" />
                <int name="delay" value="180" />
            </canvas>
            <canvas name="2" width="109" height="118">
                <vector name="origin" x="50" y="118" />
                <int name="z" value="0" />
                <int name="delay" value="180" />
            </canvas>
            <canvas name="3" width="109" height="117">
                <vector name="origin" x="50" y="117" />
                <int name="z" value="0" />
                <int name="delay" value="180" />
            </canvas>
        </imgdir>
    </imgdir>
</imgdir>