<?xml version="1.0" encoding="utf-8" standalone="yes"?>
<imgdir name="9400609.img">
    <imgdir name="info">
        <int name="forceMove" value="1" />
    </imgdir>
    <imgdir name="stand">
        <canvas name="0" width="159" height="120">
            <vector name="origin" x="71" y="115" />
            <int name="z" value="0" />
            <int name="delay" value="120" />
            <vector name="lt" x="-40" y="-85" />
            <vector name="rb" x="45" y="-12" />
            <vector name="head" x="-5" y="-83" />
        </canvas>
        <canvas name="1" width="160" height="116">
            <vector name="origin" x="71" y="113" />
            <int name="z" value="0" />
            <int name="delay" value="120" />
            <vector name="lt" x="-40" y="-85" />
            <vector name="rb" x="45" y="-12" />
            <vector name="head" x="-5" y="-83" />
        </canvas>
        <canvas name="2" width="162" height="121">
            <vector name="origin" x="71" y="119" />
            <int name="z" value="0" />
            <int name="delay" value="120" />
            <vector name="lt" x="-40" y="-85" />
            <vector name="rb" x="45" y="-12" />
            <vector name="head" x="-5" y="-83" />
        </canvas>
        <canvas name="3" width="164" height="126">
            <vector name="origin" x="71" y="122" />
            <int name="z" value="0" />
            <int name="delay" value="120" />
            <vector name="lt" x="-40" y="-85" />
            <vector name="rb" x="45" y="-12" />
            <vector name="head" x="-5" y="-83" />
        </canvas>
        <canvas name="4" width="157" height="120">
            <vector name="origin" x="71" y="115" />
            <int name="z" value="0" />
            <int name="delay" value="120" />
            <vector name="lt" x="-40" y="-85" />
            <vector name="rb" x="45" y="-12" />
            <vector name="head" x="-5" y="-83" />
        </canvas>
        <canvas name="5" width="158" height="116">
            <vector name="origin" x="71" y="113" />
            <int name="z" value="0" />
            <int name="delay" value="120" />
            <vector name="lt" x="-40" y="-85" />
            <vector name="rb" x="45" y="-12" />
            <vector name="head" x="-5" y="-83" />
        </canvas>
        <canvas name="6" width="160" height="121">
            <vector name="origin" x="71" y="119" />
            <int name="z" value="0" />
            <int name="delay" value="120" />
            <vector name="lt" x="-40" y="-85" />
            <vector name="rb" x="45" y="-12" />
            <vector name="head" x="-5" y="-83" />
        </canvas>
        <canvas name="7" width="162" height="126">
            <vector name="origin" x="71" y="122" />
            <int name="z" value="0" />
            <int name="delay" value="120" />
            <vector name="lt" x="-40" y="-85" />
            <vector name="rb" x="45" y="-12" />
            <vector name="head" x="-5" y="-83" />
        </canvas>
    </imgdir>
    <imgdir name="move">
        <canvas name="0" width="159" height="120">
            <vector name="origin" x="71" y="115" />
            <int name="z" value="0" />
            <int name="delay" value="120" />
            <vector name="lt" x="-40" y="-85" />
            <vector name="rb" x="45" y="-12" />
            <vector name="head" x="-5" y="-83" />
        </canvas>
        <canvas name="1" width="160" height="116">
            <vector name="origin" x="71" y="113" />
            <int name="z" value="0" />
            <int name="delay" value="120" />
            <vector name="lt" x="-40" y="-85" />
            <vector name="rb" x="45" y="-12" />
            <vector name="head" x="-5" y="-83" />
        </canvas>
        <canvas name="2" width="162" height="121">
            <vector name="origin" x="71" y="119" />
            <int name="z" value="0" />
            <int name="delay" value="120" />
            <vector name="lt" x="-40" y="-85" />
            <vector name="rb" x="45" y="-12" />
            <vector name="head" x="-5" y="-83" />
        </canvas>
        <canvas name="3" width="164" height="126">
            <vector name="origin" x="71" y="122" />
            <int name="z" value="0" />
            <int name="delay" value="120" />
            <vector name="lt" x="-40" y="-85" />
            <vector name="rb" x="45" y="-12" />
            <vector name="head" x="-5" y="-83" />
        </canvas>
        <canvas name="4" width="157" height="120">
            <vector name="origin" x="71" y="115" />
            <int name="z" value="0" />
            <int name="delay" value="120" />
            <vector name="lt" x="-40" y="-85" />
            <vector name="rb" x="45" y="-12" />
            <vector name="head" x="-5" y="-83" />
        </canvas>
        <canvas name="5" width="158" height="116">
            <vector name="origin" x="71" y="113" />
            <int name="z" value="0" />
            <int name="delay" value="120" />
            <vector name="lt" x="-40" y="-85" />
            <vector name="rb" x="45" y="-12" />
            <vector name="head" x="-5" y="-83" />
        </canvas>
        <canvas name="6" width="160" height="121">
            <vector name="origin" x="71" y="119" />
            <int name="z" value="0" />
            <int name="delay" value="120" />
            <vector name="lt" x="-40" y="-85" />
            <vector name="rb" x="45" y="-12" />
            <vector name="head" x="-5" y="-83" />
        </canvas>
        <canvas name="7" width="162" height="126">
            <vector name="origin" x="71" y="122" />
            <int name="z" value="0" />
            <int name="delay" value="120" />
            <vector name="lt" x="-40" y="-85" />
            <vector name="rb" x="45" y="-12" />
            <vector name="head" x="-5" y="-83" />
        </canvas>
    </imgdir>
    <imgdir name="hit1">
        <canvas name="0" width="150" height="131">
            <vector name="origin" x="71" y="128" />
            <int name="z" value="0" />
            <int name="delay" value="90" />
            <vector name="lt" x="-40" y="-85" />
            <vector name="rb" x="45" y="-12" />
            <vector name="head" x="-5" y="-83" />
        </canvas>
        <int name="special" value="1" />
    </imgdir>
    <imgdir name="die1">
        <canvas name="0" width="159" height="120">
            <vector name="origin" x="71" y="115" />
            <int name="z" value="0" />
            <int name="delay" value="120" />
        </canvas>
        <canvas name="1" width="225" height="161">
            <vector name="origin" x="136" y="142" />
            <int name="z" value="0" />
            <int name="delay" value="120" />
        </canvas>
        <canvas name="2" width="248" height="165">
            <vector name="origin" x="157" y="143" />
            <int name="z" value="0" />
            <int name="delay" value="120" />
        </canvas>
        <canvas name="3" width="239" height="171">
            <vector name="origin" x="146" y="148" />
            <int name="z" value="0" />
            <int name="delay" value="120" />
        </canvas>
        <canvas name="4" width="245" height="162">
            <vector name="origin" x="159" y="143" />
            <int name="z" value="0" />
            <int name="delay" value="120" />
        </canvas>
        <canvas name="5" width="201" height="162">
            <vector name="origin" x="127" y="143" />
            <int name="z" value="0" />
            <int name="delay" value="120" />
        </canvas>
        <canvas name="6" width="213" height="163">
            <vector name="origin" x="157" y="144" />
            <int name="z" value="0" />
            <int name="delay" value="120" />
        </canvas>
        <canvas name="7" width="163" height="162">
            <vector name="origin" x="138" y="143" />
            <int name="z" value="0" />
            <int name="delay" value="120" />
        </canvas>
        <canvas name="8" width="180" height="165">
            <vector name="origin" x="157" y="143" />
            <int name="z" value="0" />
            <int name="delay" value="120" />
        </canvas>
        <canvas name="9" width="169" height="175">
            <vector name="origin" x="146" y="148" />
            <int name="z" value="0" />
            <int name="delay" value="120" />
        </canvas>
        <canvas name="10" width="165" height="178">
            <vector name="origin" x="159" y="157" />
            <int name="z" value="0" />
            <int name="delay" value="120" />
        </canvas>
        <canvas name="11" width="136" height="176">
            <vector name="origin" x="127" y="153" />
            <int name="z" value="0" />
            <int name="delay" value="120" />
        </canvas>
        <uol name="12" value="10" />
        <uol name="13" value="11" />
        <uol name="14" value="10" />
        <uol name="15" value="11" />
        <uol name="16" value="10" />
        <uol name="17" value="11" />
        <uol name="19" value="10" />
        <uol name="20" value="11" />
        <uol name="21" value="10" />
        <uol name="22" value="11" />
        <uol name="23" value="10" />
        <uol name="24" value="11" />
        <uol name="25" value="10" />
        <uol name="26" value="11" />
        <int name="special" value="1" />
    </imgdir>
</imgdir>